forthright/.DS_Store
forthright/__init__.py
forthright/forthright.py
forthright-0.0.6.dist-info/WHEEL
forthright-0.0.6.dist-info/METADATA
forthright-0.0.6.dist-info/RECORD
