Metadata-Version: 2.3
Name: forthright
Version: 0.0.6
Summary: Allows you to seemingly call a server function directly from the client.
Author-email: Marius Facktor <mariusfacktor@gmail.com>
Requires-Python: >=3.9
Classifier: Programming Language :: Python :: 3
Classifier: License :: OSI Approved :: MIT License
Classifier: Operating System :: OS Independent
Project-URL: Homepage, https://github.com/mariusfacktor/forthright
Project-URL: Issues, https://github.com/mariusfacktor/forthright/issues
